aiogram_broadcaster/__init__.py
aiogram_broadcaster/__meta__.py
aiogram_broadcaster/broadcaster.py
aiogram_broadcaster/py.typed
aiogram_broadcaster/contents/__init__.py
aiogram_broadcaster/contents/animation.py
aiogram_broadcaster/contents/audio.py
aiogram_broadcaster/contents/base.py
aiogram_broadcaster/contents/chat_action.py
aiogram_broadcaster/contents/contact.py
aiogram_broadcaster/contents/dice.py
aiogram_broadcaster/contents/document.py
aiogram_broadcaster/contents/from_chat_copy_message.py
aiogram_broadcaster/contents/from_chat_copy_messages.py
aiogram_broadcaster/contents/from_chat_forward_message.py
aiogram_broadcaster/contents/from_chat_forward_messages.py
aiogram_broadcaster/contents/game.py
aiogram_broadcaster/contents/invoice.py
aiogram_broadcaster/contents/location.py
aiogram_broadcaster/contents/media_group.py
aiogram_broadcaster/contents/message_copy.py
aiogram_broadcaster/contents/message_forward.py
aiogram_broadcaster/contents/message_send.py
aiogram_broadcaster/contents/paid_media.py
aiogram_broadcaster/contents/photo.py
aiogram_broadcaster/contents/poll.py
aiogram_broadcaster/contents/sticker.py
aiogram_broadcaster/contents/text.py
aiogram_broadcaster/contents/venue.py
aiogram_broadcaster/contents/video.py
aiogram_broadcaster/contents/video_note.py
aiogram_broadcaster/contents/voice.py
aiogram_broadcaster/contents/adapters/__init__.py
aiogram_broadcaster/contents/adapters/lazy.py
aiogram_broadcaster/contents/adapters/mapped.py
aiogram_broadcaster/event/__init__.py
aiogram_broadcaster/event/event.py
aiogram_broadcaster/event/manager.py
aiogram_broadcaster/event/observer.py
aiogram_broadcaster/intervals/__init__.py
aiogram_broadcaster/intervals/base.py
aiogram_broadcaster/intervals/period.py
aiogram_broadcaster/intervals/simple.py
aiogram_broadcaster/mailer/__init__.py
aiogram_broadcaster/mailer/chats.py
aiogram_broadcaster/mailer/container.py
aiogram_broadcaster/mailer/group.py
aiogram_broadcaster/mailer/mailer.py
aiogram_broadcaster-0.6.8.dist-info/METADATA
aiogram_broadcaster-0.6.8.dist-info/WHEEL
aiogram_broadcaster-0.6.8.dist-info/licenses/LICENSE
aiogram_broadcaster-0.6.8.dist-info/RECORD
