Metadata-Version: 2.4
Name: aiogram_broadcaster
Version: 0.6.8
Summary: A lightweight aiogram-based library for broadcasting Telegram messages.
Project-URL: Homepage, https://github.com/loRes228/aiogram_broadcaster.git
Project-URL: Documentation, https://github.com/loRes228/aiogram_broadcaster/wiki
Project-URL: Source code, https://github.com/loRes228/aiogram_broadcaster.git
Project-URL: Issue Tracker, https://github.com/loRes228/aiogram_broadcaster/issues
Author: LORES
Maintainer: LORES
License: MIT License
License-File: LICENSE
Keywords: api,asyncio,boadcasting,bot,broadcast,broadcaster,framework,mailing,mailing-system,telegram,wrapper
Classifier: Development Status :: 3 - Alpha
Classifier: Framework :: AsyncIO
Classifier: Intended Audience :: Developers
Classifier: License :: OSI Approved :: MIT License
Classifier: Operating System :: OS Independent
Classifier: Programming Language :: Python :: 3
Classifier: Programming Language :: Python :: 3.9
Classifier: Programming Language :: Python :: 3.10
Classifier: Programming Language :: Python :: 3.11
Classifier: Programming Language :: Python :: 3.12
Classifier: Topic :: Software Development :: Libraries :: Application Frameworks
Classifier: Topic :: Software Development :: Libraries :: Python Modules
Classifier: Typing :: Typed
Requires-Python: >=3.9
Requires-Dist: aiogram>=3.22.0
Provides-Extra: all
Requires-Dist: jinja2>=3.0.0; extra == 'all'
Requires-Dist: motor-types>=1.0.0b4; extra == 'all'
Requires-Dist: motor>=3.0.0; extra == 'all'
Requires-Dist: mypy>=1.14.0; extra == 'all'
Requires-Dist: pymongo>=4.0.0; extra == 'all'
Requires-Dist: pytest-asyncio~=0.23.0; extra == 'all'
Requires-Dist: pytest~=8.3.0; extra == 'all'
Requires-Dist: redis[hiredis]>=5.0.0; extra == 'all'
Requires-Dist: ruff>=0.8.6; extra == 'all'
Requires-Dist: sqlalchemy>=2.0.0; extra == 'all'
Requires-Dist: types-aiofiles>=24.1.0; extra == 'all'
Provides-Extra: butcher
Requires-Dist: jinja2>=3.0.0; extra == 'butcher'
Provides-Extra: dev
Requires-Dist: motor-types>=1.0.0b4; extra == 'dev'
Requires-Dist: mypy>=1.14.0; extra == 'dev'
Requires-Dist: ruff>=0.8.6; extra == 'dev'
Requires-Dist: types-aiofiles>=24.1.0; extra == 'dev'
Provides-Extra: jinja
Requires-Dist: jinja2>=3.0.0; extra == 'jinja'
Provides-Extra: mongo
Requires-Dist: pymongo>=4.0.0; extra == 'mongo'
Provides-Extra: motor
Requires-Dist: motor>=3.0.0; extra == 'motor'
Provides-Extra: redis
Requires-Dist: redis[hiredis]>=5.0.0; extra == 'redis'
Provides-Extra: sqlalchemy
Requires-Dist: sqlalchemy>=2.0.0; extra == 'sqlalchemy'
Provides-Extra: test
Requires-Dist: pytest-asyncio~=0.23.0; extra == 'test'
Requires-Dist: pytest~=8.3.0; extra == 'test'
